sgx_pck_extension-0.1.4.dist-info/METADATA
sgx_pck_extension-0.1.4.dist-info/WHEEL
sgx_pck_extension/py.typed
sgx_pck_extension/__init__.py
sgx_pck_extension/__pycache__/__init__.cpython-38.pyc
sgx_pck_extension/_lib_sgx_pck_extension.abi3.so
sgx_pck_extension-0.1.4.dist-info/RECORD
