Metadata-Version: 2.1
Name: sgx-pck-extension
Version: 0.1.4
Classifier: Programming Language :: Rust
Classifier: Programming Language :: Python :: Implementation :: CPython
Classifier: Programming Language :: Python :: Implementation :: PyPy
Requires-Dist: cryptography >=40.0.2, <40.1.0
Requires-Python: >=3.8
